{"id:": "/div[1]", "tag": "div", "attributes": {"type": "article", "{http://www.w3.org/XML/1998/namespace}id": "MG-1708-04_22"}, "children": [{"id": "/div[1]/head[1]", "tag": "head", "children": [{"id": "/div[1]/head[1]/text()[1]", "text": "Epitre à son Altesse Monseigneur le Duc de Vendosme"}]}, {"id": "/div[1]/bibl[1]", "tag": "bibl", "children": [{"id": "/div[1]/bibl[1]/title[1]", "tag": "title", "children": [{"id": "/div[1]/bibl[1]/title[1]/text()[1]", "text": "Mercure galant"}]}, {"id": "/div[1]/bibl[1]/text()[1]", "text": ", avril 1708 [tome 4], p. 22-34."}]}, {"id": "/div[1]/p[1]", "tag": "p", "children": []}, {"id": "/div[1]/p[2]", "tag": "p", "children": [{"id": "/div[1]/p[2]/text()[1]", "text": "À peine Mr l’Abbé Regnier eut-il cessé de parler, que Mr de Campistron, Academicien, & Secretaire des Commandemens de Monsieur le Duc de Vendosme, lut l’Epitre suivante, adressée à ce Prince."}]}, {"id": "/div[1]/quote[1]", "tag": "quote", "children": [{"id": "/div[1]/quote[1]/label[1]", "tag": "label", "children": [{"id": "/div[1]/quote[1]/label[1]/text()[1]", "text": "EPITRE À SON ALTESSE MONSEIGNEUR LE DUC DE VENDOSME."}]}, {"id": "/div[1]/quote[1]/lg[1]", "tag": "lg", "children": [{"id": "/div[1]/quote[1]/lg[1]/l[1]", "tag": "l", "children": [{"id": "/div[1]/quote[1]/lg[1]/l[1]/hi[1]", "tag": "hi", "children": [{"id": "/div[1]/quote[1]/lg[1]/l[1]/hi[1]/text()[1]", "text": "O toy, qui seul peut-estre au sortir de l’Enfance"}], "attributes": {"rend": "i"}}]}, {"id": "/div[1]/quote[1]/lg[1]/l[2]", "tag": "l", "children": [{"id": "/div[1]/quote[1]/lg[1]/l[2]/hi[1]", "tag": "hi", "children": [{"id": "/div[1]/quote[1]/lg[1]/l[2]/hi[1]/text()[1]", "text": "Sçûs du faux, & du vray, faire la difference,"}], "attributes": {"rend": "i"}}]}, {"id": "/div[1]/quote[1]/lg[1]/l[3]", "tag": "l", "children": [{"id": "/div[1]/quote[1]/lg[1]/l[3]/hi[1]", "tag": "hi", "children": [{"id": "/div[1]/quote[1]/lg[1]/l[3]/hi[1]/text()[1]", "text": "Et préferant à tout l’austere verité,"}], "attributes": {"rend": "i"}}]}, {"id": "/div[1]/quote[1]/lg[1]/l[4]", "tag": "l", "children": [{"id": "/div[1]/quote[1]/lg[1]/l[4]/hi[1]", "tag": "hi", "children": [{"id": "/div[1]/quote[1]/lg[1]/l[4]/hi[1]/text()[1]", "text": "Joüir de la Grandeur avec simplicité,"}], "attributes": {"rend": "i"}}]}, {"id": "/div[1]/quote[1]/lg[1]/l[5]", "tag": "l", "children": [{"id": "/div[1]/quote[1]/lg[1]/l[5]/hi[1]", "tag": "hi", "children": [{"id": "/div[1]/quote[1]/lg[1]/l[5]/hi[1]/text()[1]", "text": "Qui sans montrer jamais de servile bassesse"}], "attributes": {"rend": "i"}}]}, {"id": "/div[1]/quote[1]/lg[1]/l[6]", "tag": "l", "children": [{"id": "/div[1]/quote[1]/lg[1]/l[6]/hi[1]", "tag": "hi", "children": [{"id": "/div[1]/quote[1]/lg[1]/l[6]/hi[1]/text()[1]", "text": "Ignorant de la Cour les détours & l’adresse,"}], "attributes": {"rend": "i"}}]}, {"id": "/div[1]/quote[1]/lg[1]/l[7]", "tag": "l", "children": [{"id": "/div[1]/quote[1]/lg[1]/l[7]/hi[1]", "tag": "hi", "children": [{"id": "/div[1]/quote[1]/lg[1]/l[7]/hi[1]/text()[1]", "text": "Par ta seule vertu, ton courage & ta foy,"}], "attributes": {"rend": "i"}}]}, {"id": "/div[1]/quote[1]/lg[1]/l[8]", "tag": "l", "children": [{"id": "/div[1]/quote[1]/lg[1]/l[8]/hi[1]", "tag": "hi", "children": [{"id": "/div[1]/quote[1]/lg[1]/l[8]/hi[1]/text()[1]", "text": "Possede & l’estime, & le cœur de ton Roy,"}], "attributes": {"rend": "i"}}]}, {"id": "/div[1]/quote[1]/lg[1]/l[9]", "tag": "l", "children": [{"id": "/div[1]/quote[1]/lg[1]/l[9]/hi[1]", "tag": "hi", "children": [{"id": "/div[1]/quote[1]/lg[1]/l[9]/hi[1]/text()[1]", "text": "Vendosme"}], "attributes": {"rend": "sc"}}, {"id": "/div[1]/quote[1]/lg[1]/l[9]/hi[2]", "tag": "hi", "children": [{"id": "/div[1]/quote[1]/lg[1]/l[9]/hi[2]/text()[1]", "text": "dans ces traits qu’en toy l’on voit paroistre,"}], "attributes": {"rend": "i"}}]}, {"id": "/div[1]/quote[1]/lg[1]/l[10]", "tag": "l", "children": [{"id": "/div[1]/quote[1]/lg[1]/l[10]/hi[1]", "tag": "hi", "children": [{"id": "/div[1]/quote[1]/lg[1]/l[10]/hi[1]/text()[1]", "text": "Sans attendre ton nom, l’on doit te reconnoistre."}], "attributes": {"rend": "i"}}]}, {"id": "/div[1]/quote[1]/lg[1]/l[11]", "tag": "l", "children": [{"id": "/div[1]/quote[1]/lg[1]/l[11]/text()[1]", "text": " "}, {"id": "/div[1]/quote[1]/lg[1]/l[11]/hi[1]", "tag": "hi", "children": [{"id": "/div[1]/quote[1]/lg[1]/l[11]/hi[1]/text()[1]", "text": "Cependant permets-moy d’exposer à tes yeux"}], "attributes": {"rend": "i"}}]}, {"id": "/div[1]/quote[1]/lg[1]/l[12]", "tag": "l", "children": [{"id": "/div[1]/quote[1]/lg[1]/l[12]/hi[1]", "tag": "hi", "children": [{"id": "/div[1]/quote[1]/lg[1]/l[12]/hi[1]/text()[1]", "text": "Quelque leger crayon de tes faits glorieux ;"}], "attributes": {"rend": "i"}}]}, {"id": "/div[1]/quote[1]/lg[1]/l[13]", "tag": "l", "children": [{"id": "/div[1]/quote[1]/lg[1]/l[13]/hi[1]", "tag": "hi", "children": [{"id": "/div[1]/quote[1]/lg[1]/l[13]/hi[1]/text()[1]", "text": "Mais ce n’est point assez, le zele qui m’enflame,"}], "attributes": {"rend": "i"}}]}, {"id": "/div[1]/quote[1]/lg[1]/l[14]", "tag": "l", "children": [{"id": "/div[1]/quote[1]/lg[1]/l[14]/hi[1]", "tag": "hi", "children": [{"id": "/div[1]/quote[1]/lg[1]/l[14]/hi[1]/text()[1]", "text": "Veut qu’avec tes exploits, je peigne encor ton ame."}], "attributes": {"rend": "i"}}]}, {"id": "/div[1]/quote[1]/lg[1]/l[15]", "tag": "l", "children": [{"id": "/div[1]/quote[1]/lg[1]/l[15]/hi[1]", "tag": "hi", "children": [{"id": "/div[1]/quote[1]/lg[1]/l[15]/hi[1]/text()[1]", "text": "Je ne me flate point ; je sçay que ce Tableau"}], "attributes": {"rend": "i"}}]}, {"id": "/div[1]/quote[1]/lg[1]/l[16]", "tag": "l", "children": [{"id": "/div[1]/quote[1]/lg[1]/l[16]/hi[1]", "tag": "hi", "children": [{"id": "/div[1]/quote[1]/lg[1]/l[16]/hi[1]/text()[1]", "text": "Meriteroit sans doute un plus hardi pinceau,"}], "attributes": {"rend": "i"}}]}, {"id": "/div[1]/quote[1]/lg[1]/l[17]", "tag": "l", "children": [{"id": "/div[1]/quote[1]/lg[1]/l[17]/hi[1]", "tag": "hi", "children": [{"id": "/div[1]/quote[1]/lg[1]/l[17]/hi[1]/text()[1]", "text": "Que le mien est peu propre à finir cet ouvrage ;"}], "attributes": {"rend": "i"}}]}, {"id": "/div[1]/quote[1]/lg[1]/l[18]", "tag": "l", "children": [{"id": "/div[1]/quote[1]/lg[1]/l[18]/hi[1]", "tag": "hi", "children": [{"id": "/div[1]/quote[1]/lg[1]/l[18]/hi[1]/text()[1]", "text": "Mais si je l’entreprends, j’ay du moins l’avantage"}], "attributes": {"rend": "i"}}]}, {"id": "/div[1]/quote[1]/lg[1]/l[19]", "tag": "l", "children": [{"id": "/div[1]/quote[1]/lg[1]/l[19]/hi[1]", "tag": "hi", "children": [{"id": "/div[1]/quote[1]/lg[1]/l[19]/hi[1]/text()[1]", "text": "Que cinq Lustres entiers à ta suite attaché"}], "attributes": {"rend": "i"}}]}, {"id": "/div[1]/quote[1]/lg[1]/l[20]", "tag": "l", "children": [{"id": "/div[1]/quote[1]/lg[1]/l[20]/hi[1]", "tag": "hi", "children": [{"id": "/div[1]/quote[1]/lg[1]/l[20]/hi[1]/text()[1]", "text": "Des secrets de ton cœur, rien ne me fut caché,"}], "attributes": {"rend": "i"}}]}, {"id": "/div[1]/quote[1]/lg[1]/l[21]", "tag": "l", "children": [{"id": "/div[1]/quote[1]/lg[1]/l[21]/hi[1]", "tag": "hi", "children": [{"id": "/div[1]/quote[1]/lg[1]/l[21]/hi[1]/text()[1]", "text": "Et que témoin des faits qui t’ont comblé de gloire,"}], "attributes": {"rend": "i"}}]}, {"id": "/div[1]/quote[1]/lg[1]/l[22]", "tag": "l", "children": [{"id": "/div[1]/quote[1]/lg[1]/l[22]/hi[1]", "tag": "hi", "children": [{"id": "/div[1]/quote[1]/lg[1]/l[22]/hi[1]/text()[1]", "text": "Il doit m’estre permis d’en raconter l’histoire."}], "attributes": {"rend": "i"}}]}, {"id": "/div[1]/quote[1]/lg[1]/l[23]", "tag": "l", "children": [{"id": "/div[1]/quote[1]/lg[1]/l[23]/text()[1]", "text": " "}, {"id": "/div[1]/quote[1]/lg[1]/l[23]/hi[1]", "tag": "hi", "children": [{"id": "/div[1]/quote[1]/lg[1]/l[23]/hi[1]/text()[1]", "text": "Quel autre plus fameux par ses travaux guerriers"}], "attributes": {"rend": "i"}}]}, {"id": "/div[1]/quote[1]/lg[1]/l[24]", "tag": "l", "children": [{"id": "/div[1]/quote[1]/lg[1]/l[24]/hi[1]", "tag": "hi", "children": [{"id": "/div[1]/quote[1]/lg[1]/l[24]/hi[1]/text()[1]", "text": "En differents climats cuëillit plus de lauriers ?"}], "attributes": {"rend": "i"}}]}, {"id": "/div[1]/quote[1]/lg[1]/l[25]", "tag": "l", "children": [{"id": "/div[1]/quote[1]/lg[1]/l[25]/hi[1]", "tag": "hi", "children": [{"id": "/div[1]/quote[1]/lg[1]/l[25]/hi[1]/text()[1]", "text": "Quand tu courus chercher la guerre & les alarmes,"}], "attributes": {"rend": "i"}}]}, {"id": "/div[1]/quote[1]/lg[1]/l[26]", "tag": "l", "children": [{"id": "/div[1]/quote[1]/lg[1]/l[26]/hi[1]", "tag": "hi", "children": [{"id": "/div[1]/quote[1]/lg[1]/l[26]/hi[1]/text()[1]", "text": "Rien n’égala l’éclat de tes premieres armes,"}], "attributes": {"rend": "i"}}]}, {"id": "/div[1]/quote[1]/lg[1]/l[27]", "tag": "l", "children": [{"id": "/div[1]/quote[1]/lg[1]/l[27]/hi[1]", "tag": "hi", "children": [{"id": "/div[1]/quote[1]/lg[1]/l[27]/hi[1]/text()[1]", "text": "Et l’on jugea dès lors par ces nobles essais,"}], "attributes": {"rend": "i"}}]}, {"id": "/div[1]/quote[1]/lg[1]/l[28]", "tag": "l", "children": [{"id": "/div[1]/quote[1]/lg[1]/l[28]/hi[1]", "tag": "hi", "children": [{"id": "/div[1]/quote[1]/lg[1]/l[28]/hi[1]/text()[1]", "text": "Quels devoient estre un jour ta gloire & tes succez ;"}], "attributes": {"rend": "i"}}]}, {"id": "/div[1]/quote[1]/lg[1]/l[29]", "tag": "l", "children": [{"id": "/div[1]/quote[1]/lg[1]/l[29]/hi[1]", "tag": "hi", "children": [{"id": "/div[1]/quote[1]/lg[1]/l[29]/hi[1]/text()[1]", "text": "Turenne"}], "attributes": {"rend": "sc"}}, {"id": "/div[1]/quote[1]/lg[1]/l[29]/hi[2]", "tag": "hi", "children": [{"id": "/div[1]/quote[1]/lg[1]/l[29]/hi[2]/text()[1]", "text": "en ta faveur rendit ce témoignage,"}], "attributes": {"rend": "i"}}]}, {"id": "/div[1]/quote[1]/lg[1]/l[30]", "tag": "l", "children": [{"id": "/div[1]/quote[1]/lg[1]/l[30]/hi[1]", "tag": "hi", "children": [{"id": "/div[1]/quote[1]/lg[1]/l[30]/hi[1]/text()[1]", "text": "Crequy"}], "attributes": {"rend": "sc"}}, {"id": "/div[1]/quote[1]/lg[1]/l[30]/hi[2]", "tag": "hi", "children": [{"id": "/div[1]/quote[1]/lg[1]/l[30]/hi[2]/text()[1]", "text": "te consulta sans égard à ton âge,"}], "attributes": {"rend": "i"}}]}, {"id": "/div[1]/quote[1]/lg[1]/l[31]", "tag": "l", "children": [{"id": "/div[1]/quote[1]/lg[1]/l[31]/hi[1]", "tag": "hi", "children": [{"id": "/div[1]/quote[1]/lg[1]/l[31]/hi[1]/text()[1]", "text": "Tu leur parus formé pour les premiers emplois ;"}], "attributes": {"rend": "i"}}]}, {"id": "/div[1]/quote[1]/lg[1]/l[32]", "tag": "l", "children": [{"id": "/div[1]/quote[1]/lg[1]/l[32]/hi[1]", "tag": "hi", "children": [{"id": "/div[1]/quote[1]/lg[1]/l[32]/hi[1]/text()[1]", "text": "Et si-tost que l’armée a marché sous tes loix,"}], "attributes": {"rend": "i"}}]}, {"id": "/div[1]/quote[1]/lg[1]/l[33]", "tag": "l", "children": [{"id": "/div[1]/quote[1]/lg[1]/l[33]/hi[1]", "tag": "hi", "children": [{"id": "/div[1]/quote[1]/lg[1]/l[33]/hi[1]/text()[1]", "text": "L’Ebre, le Pô, l’Escaut, estonnez de ta gloire"}], "attributes": {"rend": "i"}}]}, {"id": "/div[1]/quote[1]/lg[1]/l[34]", "tag": "l", "children": [{"id": "/div[1]/quote[1]/lg[1]/l[34]/hi[1]", "tag": "hi", "children": [{"id": "/div[1]/quote[1]/lg[1]/l[34]/hi[1]/text()[1]", "text": "Sur leurs rives, t’ont vû ramener la victoire,"}], "attributes": {"rend": "i"}}]}, {"id": "/div[1]/quote[1]/lg[1]/l[35]", "tag": "l", "children": [{"id": "/div[1]/quote[1]/lg[1]/l[35]/hi[1]", "tag": "hi", "children": [{"id": "/div[1]/quote[1]/lg[1]/l[35]/hi[1]/text()[1]", "text": "Et dans les mêmes lieux où le sort en courroux"}], "attributes": {"rend": "i"}}]}, {"id": "/div[1]/quote[1]/lg[1]/l[36]", "tag": "l", "children": [{"id": "/div[1]/quote[1]/lg[1]/l[36]/hi[1]", "tag": "hi", "children": [{"id": "/div[1]/quote[1]/lg[1]/l[36]/hi[1]/text()[1]", "text": "Nous avoit accablez des plus funestes coups,"}], "attributes": {"rend": "i"}}]}, {"id": "/div[1]/quote[1]/lg[1]/l[37]", "tag": "l", "children": [{"id": "/div[1]/quote[1]/lg[1]/l[37]/hi[1]", "tag": "hi", "children": [{"id": "/div[1]/quote[1]/lg[1]/l[37]/hi[1]/text()[1]", "text": "Trois fois de ta valeur la foudre vangeresse"}], "attributes": {"rend": "i"}}]}, {"id": "/div[1]/quote[1]/lg[1]/l[38]", "tag": "l", "children": [{"id": "/div[1]/quote[1]/lg[1]/l[38]/hi[1]", "tag": "hi", "children": [{"id": "/div[1]/quote[1]/lg[1]/l[38]/hi[1]/text()[1]", "text": "Changer des jours de deüil, en des jours d’allegresse,"}], "attributes": {"rend": "i"}}]}, {"id": "/div[1]/quote[1]/lg[1]/l[39]", "tag": "l", "children": [{"id": "/div[1]/quote[1]/lg[1]/l[39]/hi[1]", "tag": "hi", "children": [{"id": "/div[1]/quote[1]/lg[1]/l[39]/hi[1]/text()[1]", "text": "Ranimer des soldats qu’on croyoit aux abois,"}], "attributes": {"rend": "i"}}]}, {"id": "/div[1]/quote[1]/lg[1]/l[40]", "tag": "l", "children": [{"id": "/div[1]/quote[1]/lg[1]/l[40]/hi[1]", "tag": "hi", "children": [{"id": "/div[1]/quote[1]/lg[1]/l[40]/hi[1]/text()[1]", "text": "Et reparer par tout l’honneur du nom François."}], "attributes": {"rend": "i"}}]}, {"id": "/div[1]/quote[1]/lg[1]/l[41]", "tag": "l", "children": [{"id": "/div[1]/quote[1]/lg[1]/l[41]/hi[1]", "tag": "hi", "children": [{"id": "/div[1]/quote[1]/lg[1]/l[41]/hi[1]/text()[1]", "text": "Que de combats gagnez ! que de villes conquises !"}], "attributes": {"rend": "i"}}]}, {"id": "/div[1]/quote[1]/lg[1]/l[42]", "tag": "l", "children": [{"id": "/div[1]/quote[1]/lg[1]/l[42]/hi[1]", "tag": "hi", "children": [{"id": "/div[1]/quote[1]/lg[1]/l[42]/hi[1]/text()[1]", "text": "Quel nombre ! quel tissu d’heureuses entreprises !"}], "attributes": {"rend": "i"}}]}, {"id": "/div[1]/quote[1]/lg[1]/l[43]", "tag": "l", "children": [{"id": "/div[1]/quote[1]/lg[1]/l[43]/hi[1]", "tag": "hi", "children": [{"id": "/div[1]/quote[1]/lg[1]/l[43]/hi[1]/text()[1]", "text": "Nos plus fiers Ennemis tremblans ou dispersez,"}], "attributes": {"rend": "i"}}]}, {"id": "/div[1]/quote[1]/lg[1]/l[44]", "tag": "l", "children": [{"id": "/div[1]/quote[1]/lg[1]/l[44]/hi[1]", "tag": "hi", "children": [{"id": "/div[1]/quote[1]/lg[1]/l[44]/hi[1]/text()[1]", "text": "Leurs Chefs les plus fameux surpris, embarrassez,"}], "attributes": {"rend": "i"}}]}, {"id": "/div[1]/quote[1]/lg[1]/l[45]", "tag": "l", "children": [{"id": "/div[1]/quote[1]/lg[1]/l[45]/hi[1]", "tag": "hi", "children": [{"id": "/div[1]/quote[1]/lg[1]/l[45]/hi[1]/text()[1]", "text": "Des roches dont la cime osoit percer les nuës"}], "attributes": {"rend": "i"}}]}, {"id": "/div[1]/quote[1]/lg[1]/l[46]", "tag": "l", "children": [{"id": "/div[1]/quote[1]/lg[1]/l[46]/hi[1]", "tag": "hi", "children": [{"id": "/div[1]/quote[1]/lg[1]/l[46]/hi[1]/text()[1]", "text": "Par de triples remparts & des murs soûtenuës,"}], "attributes": {"rend": "i"}}]}, {"id": "/div[1]/quote[1]/lg[1]/l[47]", "tag": "l", "children": [{"id": "/div[1]/quote[1]/lg[1]/l[47]/hi[1]", "tag": "hi", "children": [{"id": "/div[1]/quote[1]/lg[1]/l[47]/hi[1]/text()[1]", "text": "Malgré tous les secours de la flamme & du fer,"}], "attributes": {"rend": "i"}}]}, {"id": "/div[1]/quote[1]/lg[1]/l[48]", "tag": "l", "children": [{"id": "/div[1]/quote[1]/lg[1]/l[48]/hi[1]", "tag": "hi", "children": [{"id": "/div[1]/quote[1]/lg[1]/l[48]/hi[1]/text()[1]", "text": "Contraintes de se rendre au milieu de l’hyver."}], "attributes": {"rend": "i"}}]}, {"id": "/div[1]/quote[1]/lg[1]/l[49]", "tag": "l", "children": [{"id": "/div[1]/quote[1]/lg[1]/l[49]/hi[1]", "tag": "hi", "children": [{"id": "/div[1]/quote[1]/lg[1]/l[49]/hi[1]/text()[1]", "text": "Mais ce qui plus que tout doit paroîstre incroyable,"}], "attributes": {"rend": "i"}}]}, {"id": "/div[1]/quote[1]/lg[1]/l[50]", "tag": "l", "children": [{"id": "/div[1]/quote[1]/lg[1]/l[50]/hi[1]", "tag": "hi", "children": [{"id": "/div[1]/quote[1]/lg[1]/l[50]/hi[1]/text()[1]", "text": "Toûjours à tes desseins le sort fut favorable,"}], "attributes": {"rend": "i"}}]}, {"id": "/div[1]/quote[1]/lg[1]/l[51]", "tag": "l", "children": [{"id": "/div[1]/quote[1]/lg[1]/l[51]/hi[1]", "tag": "hi", "children": [{"id": "/div[1]/quote[1]/lg[1]/l[51]/hi[1]/text()[1]", "text": "Les lauriers immortels qui te ceignent le front"}], "attributes": {"rend": "i"}}]}, {"id": "/div[1]/quote[1]/lg[1]/l[52]", "tag": "l", "children": [{"id": "/div[1]/quote[1]/lg[1]/l[52]/hi[1]", "tag": "hi", "children": [{"id": "/div[1]/quote[1]/lg[1]/l[52]/hi[1]/text()[1]", "text": "N’ont jamais de sa part reçû le moindre affront,"}], "attributes": {"rend": "i"}}]}, {"id": "/div[1]/quote[1]/lg[1]/l[53]", "tag": "l", "children": [{"id": "/div[1]/quote[1]/lg[1]/l[53]/hi[1]", "tag": "hi", "children": [{"id": "/div[1]/quote[1]/lg[1]/l[53]/hi[1]/text()[1]", "text": "Comme si la victoire attentive à te plaire,"}], "attributes": {"rend": "i"}}]}, {"id": "/div[1]/quote[1]/lg[1]/l[54]", "tag": "l", "children": [{"id": "/div[1]/quote[1]/lg[1]/l[54]/hi[1]", "tag": "hi", "children": [{"id": "/div[1]/quote[1]/lg[1]/l[54]/hi[1]/text()[1]", "text": "Agissoit par tes loix, ou craignoit ta colere."}], "attributes": {"rend": "i"}}]}, {"id": "/div[1]/quote[1]/lg[1]/l[55]", "tag": "l", "children": [{"id": "/div[1]/quote[1]/lg[1]/l[55]/hi[1]", "tag": "hi", "children": [{"id": "/div[1]/quote[1]/lg[1]/l[55]/hi[1]/text()[1]", "text": "Cependant si ton cœur pour la gloire formé"}], "attributes": {"rend": "i"}}]}, {"id": "/div[1]/quote[1]/lg[1]/l[56]", "tag": "l", "children": [{"id": "/div[1]/quote[1]/lg[1]/l[56]/hi[1]", "tag": "hi", "children": [{"id": "/div[1]/quote[1]/lg[1]/l[56]/hi[1]/text()[1]", "text": "De plus douces vertus n’étoit point animé"}], "attributes": {"rend": "i"}}]}, {"id": "/div[1]/quote[1]/lg[1]/l[57]", "tag": "l", "children": [{"id": "/div[1]/quote[1]/lg[1]/l[57]/hi[1]", "tag": "hi", "children": [{"id": "/div[1]/quote[1]/lg[1]/l[57]/hi[1]/text()[1]", "text": "Obtiendrois tu de nous une si haute estime ?"}], "attributes": {"rend": "i"}}]}, {"id": "/div[1]/quote[1]/lg[1]/l[58]", "tag": "l", "children": [{"id": "/div[1]/quote[1]/lg[1]/l[58]/hi[1]", "tag": "hi", "children": [{"id": "/div[1]/quote[1]/lg[1]/l[58]/hi[1]/text()[1]", "text": "Non, non, & souviens-toy de ce guerrier sublime,"}], "attributes": {"rend": "i"}}]}, {"id": "/div[1]/quote[1]/lg[1]/l[59]", "tag": "l", "children": [{"id": "/div[1]/quote[1]/lg[1]/l[59]/hi[1]", "tag": "hi", "children": [{"id": "/div[1]/quote[1]/lg[1]/l[59]/hi[1]/text()[1]", "text": "D’Alexandre qui fut le plus grand des mortels."}], "attributes": {"rend": "i"}}]}, {"id": "/div[1]/quote[1]/lg[1]/l[60]", "tag": "l", "children": [{"id": "/div[1]/quote[1]/lg[1]/l[60]/hi[1]", "tag": "hi", "children": [{"id": "/div[1]/quote[1]/lg[1]/l[60]/hi[1]/text()[1]", "text": "En vain à son courage on dressa des Autels :"}], "attributes": {"rend": "i"}}]}, {"id": "/div[1]/quote[1]/lg[1]/l[61]", "tag": "l", "children": [{"id": "/div[1]/quote[1]/lg[1]/l[61]/hi[1]", "tag": "hi", "children": [{"id": "/div[1]/quote[1]/lg[1]/l[61]/hi[1]/text()[1]", "text": "Nous reprochons encore à ce grand Alexandre"}], "attributes": {"rend": "i"}}]}, {"id": "/div[1]/quote[1]/lg[1]/l[62]", "tag": "l", "children": [{"id": "/div[1]/quote[1]/lg[1]/l[62]/hi[1]", "tag": "hi", "children": [{"id": "/div[1]/quote[1]/lg[1]/l[62]/hi[1]/text()[1]", "text": "Le meurtre de Clytus, Persepolis en cendre,"}], "attributes": {"rend": "i"}}]}, {"id": "/div[1]/quote[1]/lg[1]/l[63]", "tag": "l", "children": [{"id": "/div[1]/quote[1]/lg[1]/l[63]/hi[1]", "tag": "hi", "children": [{"id": "/div[1]/quote[1]/lg[1]/l[63]/hi[1]/text()[1]", "text": "Lisimachus forcé de combattre un Lyon,"}], "attributes": {"rend": "i"}}]}, {"id": "/div[1]/quote[1]/lg[1]/l[64]", "tag": "l", "children": [{"id": "/div[1]/quote[1]/lg[1]/l[64]/hi[1]", "tag": "hi", "children": [{"id": "/div[1]/quote[1]/lg[1]/l[64]/hi[1]/text()[1]", "text": "Et les Grecs indignez pleurant Parmenion."}], "attributes": {"rend": "i"}}]}, {"id": "/div[1]/quote[1]/lg[1]/l[65]", "tag": "l", "children": [{"id": "/div[1]/quote[1]/lg[1]/l[65]/hi[1]", "tag": "hi", "children": [{"id": "/div[1]/quote[1]/lg[1]/l[65]/hi[1]/text()[1]", "text": "La suprême valeur est précieuse & rare,"}], "attributes": {"rend": "i"}}]}, {"id": "/div[1]/quote[1]/lg[1]/l[66]", "tag": "l", "children": [{"id": "/div[1]/quote[1]/lg[1]/l[66]/hi[1]", "tag": "hi", "children": [{"id": "/div[1]/quote[1]/lg[1]/l[66]/hi[1]/text()[1]", "text": "Mais seule, & toute nuë, elle tient du Barbare."}], "attributes": {"rend": "i"}}]}, {"id": "/div[1]/quote[1]/lg[1]/l[67]", "tag": "l", "children": [{"id": "/div[1]/quote[1]/lg[1]/l[67]/hi[1]", "tag": "hi", "children": [{"id": "/div[1]/quote[1]/lg[1]/l[67]/hi[1]/text()[1]", "text": "Je veux que le Heros soit pitoyable & doux ;"}], "attributes": {"rend": "i"}}]}, {"id": "/div[1]/quote[1]/lg[1]/l[68]", "tag": "l", "children": [{"id": "/div[1]/quote[1]/lg[1]/l[68]/hi[1]", "tag": "hi", "children": [{"id": "/div[1]/quote[1]/lg[1]/l[68]/hi[1]/text()[1]", "text": "Qu’il soit fier sans orguëil, & vaillant sans courroux."}], "attributes": {"rend": "i"}}]}, {"id": "/div[1]/quote[1]/lg[1]/l[69]", "tag": "l", "children": [{"id": "/div[1]/quote[1]/lg[1]/l[69]/hi[1]", "tag": "hi", "children": [{"id": "/div[1]/quote[1]/lg[1]/l[69]/hi[1]/text()[1]", "text": "Plaindre les malheureux, soulager leur misere,"}], "attributes": {"rend": "i"}}]}, {"id": "/div[1]/quote[1]/lg[1]/l[70]", "tag": "l", "children": [{"id": "/div[1]/quote[1]/lg[1]/l[70]/hi[1]", "tag": "hi", "children": [{"id": "/div[1]/quote[1]/lg[1]/l[70]/hi[1]/text()[1]", "text": "Les aimer, leur servir de refuge & de pere,"}], "attributes": {"rend": "i"}}]}, {"id": "/div[1]/quote[1]/lg[1]/l[71]", "tag": "l", "children": [{"id": "/div[1]/quote[1]/lg[1]/l[71]/hi[1]", "tag": "hi", "children": [{"id": "/div[1]/quote[1]/lg[1]/l[71]/hi[1]/text()[1]", "text": "Estre accessible, humain, sont des dons aussi grands"}], "attributes": {"rend": "i"}}]}, {"id": "/div[1]/quote[1]/lg[1]/l[72]", "tag": "l", "children": [{"id": "/div[1]/quote[1]/lg[1]/l[72]/hi[1]", "tag": "hi", "children": [{"id": "/div[1]/quote[1]/lg[1]/l[72]/hi[1]/text()[1]", "text": "Que tous ceux, dont l’orguëil flate les Conquerans."}], "attributes": {"rend": "i"}}]}, {"id": "/div[1]/quote[1]/lg[1]/l[73]", "tag": "l", "children": [{"id": "/div[1]/quote[1]/lg[1]/l[73]/hi[1]", "tag": "hi", "children": [{"id": "/div[1]/quote[1]/lg[1]/l[73]/hi[1]/text()[1]", "text": "Rarement les voit-on briller dans le même homme."}], "attributes": {"rend": "i"}}]}, {"id": "/div[1]/quote[1]/lg[1]/l[74]", "tag": "l", "children": [{"id": "/div[1]/quote[1]/lg[1]/l[74]/hi[1]", "tag": "hi", "children": [{"id": "/div[1]/quote[1]/lg[1]/l[74]/hi[1]/text()[1]", "text": "La valeur, la prudence éclaterent dans Rome,"}], "attributes": {"rend": "i"}}]}, {"id": "/div[1]/quote[1]/lg[1]/l[75]", "tag": "l", "children": [{"id": "/div[1]/quote[1]/lg[1]/l[75]/hi[1]", "tag": "hi", "children": [{"id": "/div[1]/quote[1]/lg[1]/l[75]/hi[1]/text()[1]", "text": "Presque tous ses enfans possedoient ces vertus ;"}], "attributes": {"rend": "i"}}]}, {"id": "/div[1]/quote[1]/lg[1]/l[76]", "tag": "l", "children": [{"id": "/div[1]/quote[1]/lg[1]/l[76]/hi[1]", "tag": "hi", "children": [{"id": "/div[1]/quote[1]/lg[1]/l[76]/hi[1]/text()[1]", "text": "Mais Rome n’a produit & n’a vû qu’un Titus,"}], "attributes": {"rend": "i"}}]}, {"id": "/div[1]/quote[1]/lg[1]/l[77]", "tag": "l", "children": [{"id": "/div[1]/quote[1]/lg[1]/l[77]/hi[1]", "tag": "hi", "children": [{"id": "/div[1]/quote[1]/lg[1]/l[77]/hi[1]/text()[1]", "text": "De qui le Ciel soigneux d’achever son ouvrage,"}], "attributes": {"rend": "i"}}]}, {"id": "/div[1]/quote[1]/lg[1]/l[78]", "tag": "l", "children": [{"id": "/div[1]/quote[1]/lg[1]/l[78]/hi[1]", "tag": "hi", "children": [{"id": "/div[1]/quote[1]/lg[1]/l[78]/hi[1]/text()[1]", "text": "Voulut que la bonté fut égale au courage ;"}], "attributes": {"rend": "i"}}]}, {"id": "/div[1]/quote[1]/lg[1]/l[79]", "tag": "l", "children": [{"id": "/div[1]/quote[1]/lg[1]/l[79]/hi[1]", "tag": "hi", "children": [{"id": "/div[1]/quote[1]/lg[1]/l[79]/hi[1]/text()[1]", "text": "C’est par cette bonté, c’est par cette douceur,"}], "attributes": {"rend": "i"}}]}, {"id": "/div[1]/quote[1]/lg[1]/l[80]", "tag": "l", "children": [{"id": "/div[1]/quote[1]/lg[1]/l[80]/hi[1]", "tag": "hi", "children": [{"id": "/div[1]/quote[1]/lg[1]/l[80]/hi[1]/text()[1]", "text": "Qui fait le caractere & le prix de ton cœur,"}], "attributes": {"rend": "i"}}]}, {"id": "/div[1]/quote[1]/lg[1]/l[81]", "tag": "l", "children": [{"id": "/div[1]/quote[1]/lg[1]/l[81]/hi[1]", "tag": "hi", "children": [{"id": "/div[1]/quote[1]/lg[1]/l[81]/hi[1]/text()[1]", "text": "Et qui nous sert d’exemple à tous tant que nous sommes,"}], "attributes": {"rend": "i"}}]}, {"id": "/div[1]/quote[1]/lg[1]/l[82]", "tag": "l", "children": [{"id": "/div[1]/quote[1]/lg[1]/l[82]/hi[1]", "tag": "hi", "children": [{"id": "/div[1]/quote[1]/lg[1]/l[82]/hi[1]/text()[1]", "text": "Que nous te distinguons entre les autres hommes :"}], "attributes": {"rend": "i"}}]}, {"id": "/div[1]/quote[1]/lg[1]/l[83]", "tag": "l", "children": [{"id": "/div[1]/quote[1]/lg[1]/l[83]/hi[1]", "tag": "hi", "children": [{"id": "/div[1]/quote[1]/lg[1]/l[83]/hi[1]/text()[1]", "text": "C’est par là que ton nom aujourd’hui reveré"}], "attributes": {"rend": "i"}}]}, {"id": "/div[1]/quote[1]/lg[1]/l[84]", "tag": "l", "children": [{"id": "/div[1]/quote[1]/lg[1]/l[84]/hi[1]", "tag": "hi", "children": [{"id": "/div[1]/quote[1]/lg[1]/l[84]/hi[1]/text()[1]", "text": "Plus que par tes hauts faits, doit estre consacré,"}], "attributes": {"rend": "i"}}]}, {"id": "/div[1]/quote[1]/lg[1]/l[85]", "tag": "l", "children": [{"id": "/div[1]/quote[1]/lg[1]/l[85]/hi[1]", "tag": "hi", "children": [{"id": "/div[1]/quote[1]/lg[1]/l[85]/hi[1]/text()[1]", "text": "Et que tout l’avenir en lisant ton Histoire"}], "attributes": {"rend": "i"}}]}, {"id": "/div[1]/quote[1]/lg[1]/l[86]", "tag": "l", "children": [{"id": "/div[1]/quote[1]/lg[1]/l[86]/hi[1]", "tag": "hi", "children": [{"id": "/div[1]/quote[1]/lg[1]/l[86]/hi[1]/text()[1]", "text": "Justement attendri benira ta memoire."}], "attributes": {"rend": "i"}}]}, {"id": "/div[1]/quote[1]/lg[1]/l[87]", "tag": "l", "children": [{"id": "/div[1]/quote[1]/lg[1]/l[87]/hi[1]", "tag": "hi", "children": [{"id": "/div[1]/quote[1]/lg[1]/l[87]/hi[1]/text()[1]", "text": "C’est par là qu’entraînant tous les cœurs des soldats"}], "attributes": {"rend": "i"}}]}, {"id": "/div[1]/quote[1]/lg[1]/l[88]", "tag": "l", "children": [{"id": "/div[1]/quote[1]/lg[1]/l[88]/hi[1]", "tag": "hi", "children": [{"id": "/div[1]/quote[1]/lg[1]/l[88]/hi[1]/text()[1]", "text": "Tu leur fais avec joye accompagner tes pas,"}], "attributes": {"rend": "i"}}]}, {"id": "/div[1]/quote[1]/lg[1]/l[89]", "tag": "l", "children": [{"id": "/div[1]/quote[1]/lg[1]/l[89]/hi[1]", "tag": "hi", "children": [{"id": "/div[1]/quote[1]/lg[1]/l[89]/hi[1]/text()[1]", "text": "Quand tu cours pour servir ton Maître & ta Patrie"}], "attributes": {"rend": "i"}}]}, {"id": "/div[1]/quote[1]/lg[1]/l[90]", "tag": "l", "children": [{"id": "/div[1]/quote[1]/lg[1]/l[90]/hi[1]", "tag": "hi", "children": [{"id": "/div[1]/quote[1]/lg[1]/l[90]/hi[1]/text()[1]", "text": "D’un monde d’Ennemis reprimer la furie,"}], "attributes": {"rend": "i"}}]}, {"id": "/div[1]/quote[1]/lg[1]/l[91]", "tag": "l", "children": [{"id": "/div[1]/quote[1]/lg[1]/l[91]/hi[1]", "tag": "hi", "children": [{"id": "/div[1]/quote[1]/lg[1]/l[91]/hi[1]/text()[1]", "text": "Braver mille hazards, & prodiguant ton sang,"}], "attributes": {"rend": "i"}}]}, {"id": "/div[1]/quote[1]/lg[1]/l[92]", "tag": "l", "children": [{"id": "/div[1]/quote[1]/lg[1]/l[92]/hi[1]", "tag": "hi", "children": [{"id": "/div[1]/quote[1]/lg[1]/l[92]/hi[1]/text()[1]", "text": "Remplir tous les devoirs attachez à ton rang,"}], "attributes": {"rend": "i"}}]}, {"id": "/div[1]/quote[1]/lg[1]/l[93]", "tag": "l", "children": [{"id": "/div[1]/quote[1]/lg[1]/l[93]/hi[1]", "tag": "hi", "children": [{"id": "/div[1]/quote[1]/lg[1]/l[93]/hi[1]/text()[1]", "text": "Toutefois ne croy pas te sauver de l’envie ;"}], "attributes": {"rend": "i"}}]}, {"id": "/div[1]/quote[1]/lg[1]/l[94]", "tag": "l", "children": [{"id": "/div[1]/quote[1]/lg[1]/l[94]/hi[1]", "tag": "hi", "children": [{"id": "/div[1]/quote[1]/lg[1]/l[94]/hi[1]/text()[1]", "text": "Ses traits empoisonnez voudroient noircir ta vie."}], "attributes": {"rend": "i"}}]}, {"id": "/div[1]/quote[1]/lg[1]/l[95]", "tag": "l", "children": [{"id": "/div[1]/quote[1]/lg[1]/l[95]/hi[1]", "tag": "hi", "children": [{"id": "/div[1]/quote[1]/lg[1]/l[95]/hi[1]/text()[1]", "text": "Des Courtisans jaloux sans estre tes Rivaux"}], "attributes": {"rend": "i"}}]}, {"id": "/div[1]/quote[1]/lg[1]/l[96]", "tag": "l", "children": [{"id": "/div[1]/quote[1]/lg[1]/l[96]/hi[1]", "tag": "hi", "children": [{"id": "/div[1]/quote[1]/lg[1]/l[96]/hi[1]/text()[1]", "text": "S’efforcent d’affoiblir le prix de tes travaux,"}], "attributes": {"rend": "i"}}]}, {"id": "/div[1]/quote[1]/lg[1]/l[97]", "tag": "l", "children": [{"id": "/div[1]/quote[1]/lg[1]/l[97]/hi[1]", "tag": "hi", "children": [{"id": "/div[1]/quote[1]/lg[1]/l[97]/hi[1]/text()[1]", "text": "Et de mesler quelqu’ombre à l’éclat de ta gloire :"}], "attributes": {"rend": "i"}}]}, {"id": "/div[1]/quote[1]/lg[1]/l[98]", "tag": "l", "children": [{"id": "/div[1]/quote[1]/lg[1]/l[98]/hi[1]", "tag": "hi", "children": [{"id": "/div[1]/quote[1]/lg[1]/l[98]/hi[1]/text()[1]", "text": "Mais que peut contre toy la fureur la plus noire ?"}], "attributes": {"rend": "i"}}]}, {"id": "/div[1]/quote[1]/lg[1]/l[99]", "tag": "l", "children": [{"id": "/div[1]/quote[1]/lg[1]/l[99]/hi[1]", "tag": "hi", "children": [{"id": "/div[1]/quote[1]/lg[1]/l[99]/hi[1]/text()[1]", "text": "On n’ose t’attaquer que sur de vains sujets ;"}], "attributes": {"rend": "i"}}]}, {"id": "/div[1]/quote[1]/lg[1]/l[100]", "tag": "l", "children": [{"id": "/div[1]/quote[1]/lg[1]/l[100]/hi[1]", "tag": "hi", "children": [{"id": "/div[1]/quote[1]/lg[1]/l[100]/hi[1]/text()[1]", "text": "On s’attache à chercher de frivoles objets ;"}], "attributes": {"rend": "i"}}]}, {"id": "/div[1]/quote[1]/lg[1]/l[101]", "tag": "l", "children": [{"id": "/div[1]/quote[1]/lg[1]/l[101]/hi[1]", "tag": "hi", "children": [{"id": "/div[1]/quote[1]/lg[1]/l[101]/hi[1]/text()[1]", "text": "On voudroit que ton cœur semblable aux cœurs vulgaires"}], "attributes": {"rend": "i"}}]}, {"id": "/div[1]/quote[1]/lg[1]/l[102]", "tag": "l", "children": [{"id": "/div[1]/quote[1]/lg[1]/l[102]/hi[1]", "tag": "hi", "children": [{"id": "/div[1]/quote[1]/lg[1]/l[102]/hi[1]/text()[1]", "text": "S’occupast de desirs & de soins ordinaires,"}], "attributes": {"rend": "i"}}]}, {"id": "/div[1]/quote[1]/lg[1]/l[103]", "tag": "l", "children": [{"id": "/div[1]/quote[1]/lg[1]/l[103]/hi[1]", "tag": "hi", "children": [{"id": "/div[1]/quote[1]/lg[1]/l[103]/hi[1]/text()[1]", "text": "Qu’il s’ouvrist à l’intrigue, au faste, à l’interest,"}], "attributes": {"rend": "i"}}]}, {"id": "/div[1]/quote[1]/lg[1]/l[104]", "tag": "l", "children": [{"id": "/div[1]/quote[1]/lg[1]/l[104]/hi[1]", "tag": "hi", "children": [{"id": "/div[1]/quote[1]/lg[1]/l[104]/hi[1]/text()[1]", "text": "Et qu’il fust en un mot beaucoup moins grand qu’il n’est."}], "attributes": {"rend": "i"}}]}, {"id": "/div[1]/quote[1]/lg[1]/l[105]", "tag": "l", "children": [{"id": "/div[1]/quote[1]/lg[1]/l[105]/hi[1]", "tag": "hi", "children": [{"id": "/div[1]/quote[1]/lg[1]/l[105]/hi[1]/text()[1]", "text": "De tous ces envieux l’odieuse Critique,"}], "attributes": {"rend": "i"}}]}, {"id": "/div[1]/quote[1]/lg[1]/l[106]", "tag": "l", "children": [{"id": "/div[1]/quote[1]/lg[1]/l[106]/hi[1]", "tag": "hi", "children": [{"id": "/div[1]/quote[1]/lg[1]/l[106]/hi[1]/text()[1]", "text": "En voulant t’abaisser fait ton Panegyrique."}], "attributes": {"rend": "i"}}]}, {"id": "/div[1]/quote[1]/lg[1]/l[107]", "tag": "l", "children": [{"id": "/div[1]/quote[1]/lg[1]/l[107]/hi[1]", "tag": "hi", "children": [{"id": "/div[1]/quote[1]/lg[1]/l[107]/hi[1]/text()[1]", "text": "Vis donc ; & poursuivant ta course & tes projets,"}], "attributes": {"rend": "i"}}]}, {"id": "/div[1]/quote[1]/lg[1]/l[108]", "tag": "l", "children": [{"id": "/div[1]/quote[1]/lg[1]/l[108]/hi[1]", "tag": "hi", "children": [{"id": "/div[1]/quote[1]/lg[1]/l[108]/hi[1]/text()[1]", "text": "En triomphant toûjours ramene-nous la Paix."}], "attributes": {"rend": "i"}}]}, {"id": "/div[1]/quote[1]/lg[1]/l[109]", "tag": "l", "children": [{"id": "/div[1]/quote[1]/lg[1]/l[109]/hi[1]", "tag": "hi", "children": [{"id": "/div[1]/quote[1]/lg[1]/l[109]/hi[1]/text()[1]", "text": "Enfin fasse le Ciel secondant mon envie"}], "attributes": {"rend": "i"}}]}, {"id": "/div[1]/quote[1]/lg[1]/l[110]", "tag": "l", "children": [{"id": "/div[1]/quote[1]/lg[1]/l[110]/hi[1]", "tag": "hi", "children": [{"id": "/div[1]/quote[1]/lg[1]/l[110]/hi[1]/text()[1]", "text": "Qu’un bonheur toûjours pur accompagne ta vie,"}], "attributes": {"rend": "i"}}]}, {"id": "/div[1]/quote[1]/lg[1]/l[111]", "tag": "l", "children": [{"id": "/div[1]/quote[1]/lg[1]/l[111]/hi[1]", "tag": "hi", "children": [{"id": "/div[1]/quote[1]/lg[1]/l[111]/hi[1]/text()[1]", "text": "Que les ans de Nestor pour toy renouvellez"}], "attributes": {"rend": "i"}}]}, {"id": "/div[1]/quote[1]/lg[1]/l[112]", "tag": "l", "children": [{"id": "/div[1]/quote[1]/lg[1]/l[112]/hi[1]", "tag": "hi", "children": [{"id": "/div[1]/quote[1]/lg[1]/l[112]/hi[1]/text()[1]", "text": "Aprés leur dernier jour soient encor redoublez ;"}], "attributes": {"rend": "i"}}]}, {"id": "/div[1]/quote[1]/lg[1]/l[113]", "tag": "l", "children": [{"id": "/div[1]/quote[1]/lg[1]/l[113]/hi[1]", "tag": "hi", "children": [{"id": "/div[1]/quote[1]/lg[1]/l[113]/hi[1]/text()[1]", "text": "Et pour combler les vœux, que pour toy l’on peut faire,"}], "attributes": {"rend": "i"}}]}, {"id": "/div[1]/quote[1]/lg[1]/l[114]", "tag": "l", "children": [{"id": "/div[1]/quote[1]/lg[1]/l[114]/hi[1]", "tag": "hi", "children": [{"id": "/div[1]/quote[1]/lg[1]/l[114]/hi[1]/text()[1]", "text": "Que toûjours à"}], "attributes": {"rend": "i"}}, {"id": "/div[1]/quote[1]/lg[1]/l[114]/hi[2]", "tag": "hi", "children": [{"id": "/div[1]/quote[1]/lg[1]/l[114]/hi[2]/text()[1]", "text": "Louis"}], "attributes": {"rend": "sc"}}, {"id": "/div[1]/quote[1]/lg[1]/l[114]/hi[3]", "tag": "hi", "children": [{"id": "/div[1]/quote[1]/lg[1]/l[114]/hi[3]/text()[1]", "text": "tu sois digne de plaire."}], "attributes": {"rend": "i"}}]}]}]}]}