{"id:": "/div[1]", "tag": "div", "attributes": {"type": "article", "{http://www.w3.org/XML/1998/namespace}id": "MG-1692-08a_161", "resp": "wordpro"}, "children": [{"id": "/div[1]/head[1]", "tag": "head", "children": [{"id": "/div[1]/head[1]/text()[1]", "text": "Avis aux Flamans"}]}, {"id": "/div[1]/bibl[1]", "tag": "bibl", "children": [{"id": "/div[1]/bibl[1]/title[1]", "tag": "title", "children": [{"id": "/div[1]/bibl[1]/title[1]/text()[1]", "text": "Mercure galant"}]}, {"id": "/div[1]/bibl[1]/text()[1]", "text": ", août 1692 [tome 10], p. 161-162."}]}, {"id": "/div[1]/p[1]", "tag": "p", "children": [{"id": "/div[1]/p[1]/text()[1]", "text": "Le Sonnet que vous allez lire, est de Mademoiselle de Dommaigne de la Rochehüe."}]}, {"id": "/div[1]/quote[1]", "tag": "quote", "children": [{"id": "/div[1]/quote[1]/label[1]", "tag": "label", "children": [{"id": "/div[1]/quote[1]/label[1]/text()[1]", "text": "AVIS AUX FLAMANS."}]}, {"id": "/div[1]/quote[1]/lg[1]", "tag": "lg", "children": [{"id": "/div[1]/quote[1]/lg[1]/l[1]", "tag": "l", "children": [{"id": "/div[1]/quote[1]/lg[1]/l[1]/text()[1]", "text": "Qu’attendez-vous encor, Peuples infortunez,"}], "attributes": {"rend": "i"}}, {"id": "/div[1]/quote[1]/lg[1]/l[2]", "tag": "l", "children": [{"id": "/div[1]/quote[1]/lg[1]/l[2]/text()[1]", "text": "Pour secoüer le joug d’une impuissante Ligue ?"}], "attributes": {"rend": "i"}}, {"id": "/div[1]/quote[1]/lg[1]/l[3]", "tag": "l", "children": [{"id": "/div[1]/quote[1]/lg[1]/l[3]/text()[1]", "text": "Si Guillaume en secret a conduit son intrigue,"}], "attributes": {"rend": "i"}}, {"id": "/div[1]/quote[1]/lg[1]/l[4]", "tag": "l", "children": [{"id": "/div[1]/quote[1]/lg[1]/l[4]/text()[1]", "text": "Il a forgé les fers qui vous ont enchaînez."}], "attributes": {"rend": "i"}}]}, {"id": "/div[1]/quote[1]/ab[1]", "tag": "ab", "children": [{"id": "/div[1]/quote[1]/ab[1]/text()[1]", "text": "***"}], "attributes": {"type": "ornament"}}, {"id": "/div[1]/quote[1]/lg[2]", "tag": "lg", "children": [{"id": "/div[1]/quote[1]/lg[2]/l[1]", "tag": "l", "children": [{"id": "/div[1]/quote[1]/lg[2]/l[1]/text()[1]", "text": "Tant de Princes jaloux, tant d’esprits mutinez"}], "attributes": {"rend": "i"}}, {"id": "/div[1]/quote[1]/lg[2]/l[2]", "tag": "l", "children": [{"id": "/div[1]/quote[1]/lg[2]/l[2]/text()[1]", "text": "Opposent à LOUIS une trop foible digue ;"}], "attributes": {"rend": "i"}}, {"id": "/div[1]/quote[1]/lg[2]/l[3]", "tag": "l", "children": [{"id": "/div[1]/quote[1]/lg[2]/l[3]/text()[1]", "text": "En vain pour vous sauver on sollicite, on brigue,"}], "attributes": {"rend": "i"}}, {"id": "/div[1]/quote[1]/lg[2]/l[4]", "tag": "l", "children": [{"id": "/div[1]/quote[1]/lg[2]/l[4]/text()[1]", "text": "Tous, à suivre son char vous estes destinez."}], "attributes": {"rend": "i"}}]}, {"id": "/div[1]/quote[1]/ab[2]", "tag": "ab", "children": [{"id": "/div[1]/quote[1]/ab[2]/text()[1]", "text": "***"}], "attributes": {"type": "ornament"}}, {"id": "/div[1]/quote[1]/lg[3]", "tag": "lg", "children": [{"id": "/div[1]/quote[1]/lg[3]/l[1]", "tag": "l", "children": [{"id": "/div[1]/quote[1]/lg[3]/l[1]/text()[1]", "text": "Est-ce sur l’impossible où vôtre espoir se fonde ?"}], "attributes": {"rend": "i"}}, {"id": "/div[1]/quote[1]/lg[3]/l[2]", "tag": "l", "children": [{"id": "/div[1]/quote[1]/lg[3]/l[2]/text()[1]", "text": "Croyez-vous triompher du plus grand Roy du monde,"}], "attributes": {"rend": "i"}}, {"id": "/div[1]/quote[1]/lg[3]/l[3]", "tag": "l", "children": [{"id": "/div[1]/quote[1]/lg[3]/l[3]/text()[1]", "text": "Qui seul à l’Univers peut imposer la Loy ?"}], "attributes": {"rend": "i"}}]}, {"id": "/div[1]/quote[1]/ab[3]", "tag": "ab", "children": [{"id": "/div[1]/quote[1]/ab[3]/text()[1]", "text": "***"}], "attributes": {"type": "ornament"}}, {"id": "/div[1]/quote[1]/lg[4]", "tag": "lg", "children": [{"id": "/div[1]/quote[1]/lg[4]/l[1]", "tag": "l", "children": [{"id": "/div[1]/quote[1]/lg[4]/l[1]/text()[1]", "text": "Aprés Mons & Namur quelle est vôtre esperance ?"}], "attributes": {"rend": "i"}}, {"id": "/div[1]/quote[1]/lg[4]/l[2]", "tag": "l", "children": [{"id": "/div[1]/quote[1]/lg[4]/l[2]/text()[1]", "text": "Comptez-vous sur Anvers, Ostende, & Charleroy ?"}], "attributes": {"rend": "i"}}, {"id": "/div[1]/quote[1]/lg[4]/l[3]", "tag": "l", "children": [{"id": "/div[1]/quote[1]/lg[4]/l[3]/text()[1]", "text": "Il faut les voir tomber, ou conquerir la France."}], "attributes": {"rend": "i"}}]}]}]}