{"id:": "/div[1]", "tag": "div", "attributes": {"type": "article", "{http://www.w3.org/XML/1998/namespace}id": "MG-1707-08_149", "resp": "angele"}, "children": [{"id": "/div[1]/head[1]", "tag": "head", "children": [{"id": "/div[1]/head[1]/text()[1]", "text": "Air nouveau"}]}, {"id": "/div[1]/bibl[1]", "tag": "bibl", "children": [{"id": "/div[1]/bibl[1]/title[1]", "tag": "title", "children": [{"id": "/div[1]/bibl[1]/title[1]/text()[1]", "text": "Mercure galant"}]}, {"id": "/div[1]/bibl[1]/text()[1]", "text": ", août 1707 [tome 8], p. 149-150."}]}, {"id": "/div[1]/p[1]", "tag": "p", "children": [{"id": "/div[1]/p[1]/text()[1]", "text": "Les paroles de l'Air qui suit sont de Mlle d'Alerac de la Charsse, de la Maison de la Tour du Pin en Dauphiné. Je vous ay déja envoyé plusieurs de ses Ouvrages, dont le public a esté tres-satisfait."}]}, {"id": "/div[1]/quote[1]", "tag": "quote", "children": [{"id": "/div[1]/quote[1]/label[1]", "tag": "label", "children": [{"id": "/div[1]/quote[1]/label[1]/text()[1]", "text": "AIR NOUVEAU."}]}, {"id": "/div[1]/quote[1]/note[1]", "tag": "note", "children": [{"id": "/div[1]/quote[1]/note[1]/hi[1]", "tag": "hi", "children": [{"id": "/div[1]/quote[1]/note[1]/hi[1]/text()[1]", "text": "Avis pour placer les Figures"}], "attributes": {"rend": "i"}}, {"id": "/div[1]/quote[1]/note[1]/text()[1]", "text": " : l’Air qui commence par "}, {"id": "/div[1]/quote[1]/note[1]/hi[2]", "tag": "hi", "children": [{"id": "/div[1]/quote[1]/note[1]/hi[2]/text()[1]", "text": "Cessez de me parler du Printemps"}], "attributes": {"rend": "i"}}, {"id": "/div[1]/quote[1]/note[1]/text()[2]", "text": ", doit regarder la page 149."}], "attributes": {"resp": "author", "place": "margin"}}, {"id": "/div[1]/quote[1]/lg[1]", "tag": "lg", "children": [{"id": "/div[1]/quote[1]/lg[1]/l[1]", "tag": "l", "children": [{"id": "/div[1]/quote[1]/lg[1]/l[1]/text()[1]", "text": "Cessez de me parler du Printemps & de Flore,"}], "attributes": {"rend": "i"}}, {"id": "/div[1]/quote[1]/lg[1]/l[2]", "tag": "l", "children": [{"id": "/div[1]/quote[1]/lg[1]/l[2]/text()[1]", "text": "Je détourne mes yeux de leurs touchans appas :"}], "attributes": {"rend": "i"}}, {"id": "/div[1]/quote[1]/lg[1]/l[3]", "tag": "l", "children": [{"id": "/div[1]/quote[1]/lg[1]/l[3]/text()[1]", "text": "Absente du Berger que j'aime & qui m'adore."}], "attributes": {"rend": "i"}}, {"id": "/div[1]/quote[1]/lg[1]/l[4]", "tag": "l", "children": [{"id": "/div[1]/quote[1]/lg[1]/l[4]/text()[1]", "text": "C'est assez d'éviter les horreurs du trépas,"}], "attributes": {"rend": "i"}}, {"id": "/div[1]/quote[1]/lg[1]/l[5]", "tag": "l", "children": [{"id": "/div[1]/quote[1]/lg[1]/l[5]/text()[1]", "text": "Sans songer aux plaisirs encore."}], "attributes": {"rend": "i"}}]}, {"id": "/div[1]/quote[1]/p[1]", "tag": "p", "children": [{"id": "/div[1]/quote[1]/p[1]/text()[1]", "text": "Les Vers que vous venez de lire ont esté notez par M"}, {"id": "/div[1]/quote[1]/p[1]/hi[1]", "tag": "hi", "children": [{"id": "/div[1]/quote[1]/p[1]/hi[1]/text()[1]", "text": "r"}], "attributes": {"rend": "sup"}}, {"id": "/div[1]/quote[1]/p[1]/text()[2]", "text": " Chastan de la ville d'Apt. Vous jugerez vous-même de la beauté de cet Air."}]}]}, {"id": "/div[1]/ref[1]", "tag": "ref", "children": [{"id": "/div[1]/ref[1]/figure[1]", "tag": "figure", "children": [{"id": "/div[1]/ref[1]/figure[1]/graphic[1]", "tag": "graphic", "children": [], "attributes": {"url": "images/1707-08_149.JPG"}}]}], "attributes": {"target": "images/1707-08_149.JPG"}}]}